{
  "cache_version": "stabilization-a-v1",
  "fingerprint": "6b5f404b8ba27014270460c9da111ba26b78bd7bbf0aef3a808a38db51aa8ace",
  "fingerprint_parts": {
    "fingerprint_version": 1,
    "cache_version": "stabilization-a-v1",
    "report_version": "stabilization-a-v1",
    "card_database": {
      "cards.json": {
        "exists": true,
        "size": 27933090,
        "mtime_ns": 1779812470850588900,
        "sha256": "8ee449babeb052bd8acb9ff3bd703608308a5e536fac46aa089b3d500357f4f1"
      },
      "metadata.json": {
        "exists": true,
        "size": 420,
        "mtime_ns": 1779812471111817400,
        "sha256": "067f45f8a2c30da86ef7fc4d48f74252abd07a55db84d0db16b84b54242370c4"
      },
      "latest_update_analysis.json": {
        "exists": true,
        "size": 373,
        "mtime_ns": 1779812471112822100,
        "sha256": "3668205d4eb114175de407bb26de43d2226b755656eb19ff5df4e09a11770f11"
      }
    },
    "custom_card_limits": {
      "Pot of Greed": 0,
      "Protector with Eyes of Blue": 0,
      "Strength in Unity": 0
    },
    "engine_variants": [
      "pure",
      "ritual",
      "chaos",
      "bystial",
      "horus",
      "branded",
      "board_breaker_heavy",
      "handtrap_heavy"
    ],
    "side_plan_settings": {
      "matrix_smoke_side_candidates": 4,
      "matrix_full_side_candidates": 6,
      "matrix_smoke_engine_limit": 4,
      "matrix_smoke_matchup_limit": 4
    }
  },
  "schema_version": 1,
  "value": {
    "engine_variant": "chaos",
    "matchup": "Tenpai curated profile",
    "going": "second",
    "successful_runs": 1,
    "failed_runs": 0,
    "failed_cell": false,
    "failure_rate": 0.0,
    "average_final_score": 273.32,
    "best_score": 273.32,
    "package_quality": 98.8,
    "playable_hand_rate": 1.0,
    "brick_rate": 0.0,
    "resilience_score": 8.7,
    "side_deck_score": 75.0,
    "game1_score": 273.11,
    "post_side_score": 278.65,
    "post_side_delta": 5.54,
    "post_side_valid_rate": 1.0,
    "valid_candidate_rate": 1.0,
    "side_optimization_success_rate": 1.0,
    "post_side_memory_used_rate": 0.0,
    "memory_aided_post_side_delta": 0,
    "matchup_coverage_score": 35.0,
    "choke_stop_rate": 0.87,
    "opponent_recovery_rate": 0.4438,
    "choke_coverage_score": 87.0,
    "best_interruption_overlap": 6,
    "poor_interruption_count": 0,
    "timing_precision_score": 0.7817,
    "pivot_risk_score": 0.7383,
    "best_timing_window_count": 4,
    "late_interruption_risk": 0.25,
    "early_interruption_risk": 0.25,
    "backup_line_success_rate": 0.4488,
    "graph_stop_rate": 0.78,
    "graph_pivot_rate": 0.61,
    "graph_endboard_reduction_score": 0.4875,
    "graph_best_interruption_count": 3,
    "graph_poor_interruption_count": 3,
    "graph_timing_precision_score": 0.78,
    "opponent_resource_valid_rate": 1.0,
    "opponent_resource_failure_rate": 0.0,
    "opponent_pivot_success_rate": 0.0,
    "opponent_backup_success_rate": 0.6667,
    "opponent_starter_open_rate": 0.0,
    "opponent_extender_open_rate": 0.0,
    "opponent_interruption_open_rate": 0.0,
    "opponent_brick_rate": 0.0,
    "probability_weighted_resource_valid_rate": 0.0,
    "probability_weighted_stop_rate": 0.0,
    "probability_weighted_pivot_rate": 0.0,
    "probability_weighted_backup_rate": 0.0,
    "going_first_side_score": 0.0,
    "going_second_side_score": 0.0,
    "blocked_card_violations": [],
    "best_deck": {
      "main_deck": [
        "Blue-Eyes Alternative White Dragon",
        "Blue-Eyes Jet Dragon",
        "Dragon Spirit of White",
        "Dragon Spirit of White",
        "Blue-Eyes Abyss Dragon",
        "Blue-Eyes Jet Dragon",
        "Blue-Eyes Alternative White Dragon",
        "Blue-Eyes Alternative White Dragon",
        "Blue-Eyes Abyss Dragon",
        "Blue-Eyes Jet Dragon",
        "The White Stone of Legend",
        "The White Stone of Legend",
        "Sage with Eyes of Blue",
        "Dictator of D.",
        "Sage with Eyes of Blue",
        "Bingo Machine, Go!!!",
        "Wishes for Eyes of Blue",
        "Bingo Machine, Go!!!",
        "Bingo Machine, Go!!!",
        "Wishes for Eyes of Blue",
        "The Ultimate Creature of Destruction",
        "Destined Rivals",
        "Chaos Dragon Levianeer",
        "Chaos Dragon Levianeer",
        "Chaos Dragon Levianeer",
        "Nibiru, the Primal Being",
        "Effect Veiler",
        "D.D. Crow",
        "Nibiru, the Primal Being",
        "Ghost Belle & Haunted Mansion",
        "Ghost Ogre & Snow Rabbit",
        "Book of Eclipse",
        "Dark Ruler No More",
        "Solemn Strike",
        "Solemn Judgment"
      ],
      "extra_deck": [
        "Dragon Master Knight",
        "Dragon Master Knight",
        "Blue-Eyes Spirit Dragon",
        "Blue-Eyes Tyrant Dragon",
        "Blue-Eyes Alternative Ultimate Dragon"
      ]
    },
    "recommended_side_deck": [
      [
        "Book of Eclipse",
        1
      ],
      [
        "Cosmic Cyclone",
        1
      ],
      [
        "Infinite Impermanence",
        1
      ],
      [
        "Effect Veiler",
        1
      ],
      [
        "Droll & Lock Bird",
        1
      ],
      [
        "True Light",
        1
      ],
      [
        "The Ultimate Creature of Destruction",
        1
      ],
      [
        "Droll Bird",
        1
      ],
      [
        "Dark Ruler No More",
        1
      ],
      [
        "Ash Blossom & Joyous Spring",
        1
      ],
      [
        "Zuttomozaurus",
        1
      ],
      [
        "Zuijin of the Ice Barrier",
        1
      ],
      [
        "Zubababa Knight",
        1
      ],
      [
        "Zubaba Knight",
        1
      ],
      [
        "Zubaba Buster",
        1
      ]
    ],
    "best_remembered_side_cards": [],
    "best_remembered_side_out_cards": [],
    "runs": [
      {
        "run": 1,
        "ok": true,
        "engine_variant": "chaos",
        "final_score": 273.32,
        "package_quality": 98.8,
        "playable_hand_rate": 1.0,
        "brick_rate": 0.0,
        "resilience_score": 8.7,
        "side_deck_score": 75.0,
        "game1_score": 273.11,
        "post_side_score": 278.65,
        "post_side_delta": 5.54,
        "post_side_valid": true,
        "valid_candidate_rate": 1.0,
        "optimization_used": true,
        "post_side_memory_used": false,
        "remembered_side_cards": [],
        "remembered_side_out_cards": [],
        "memory_aided_post_side_delta": 0,
        "matchup_coverage_score": 35.0,
        "choke_stop_rate": 0.87,
        "opponent_recovery_rate": 0.4438,
        "choke_coverage_score": 87.0,
        "best_interruption_overlap": 6,
        "poor_interruption_count": 0,
        "timing_precision_score": 0.7817,
        "pivot_risk_score": 0.7383,
        "best_timing_window_count": 4,
        "late_interruption_risk": 0.25,
        "early_interruption_risk": 0.25,
        "backup_line_success_rate": 0.4488,
        "graph_stop_rate": 0.78,
        "graph_pivot_rate": 0.61,
        "graph_endboard_reduction_score": 0.4875,
        "graph_best_interruption_count": 3,
        "graph_poor_interruption_count": 3,
        "graph_timing_precision_score": 0.78,
        "opponent_resource_valid_rate": 1.0,
        "opponent_resource_failure_rate": 0.0,
        "opponent_pivot_success_rate": 0.0,
        "opponent_backup_success_rate": 0.6667,
        "opponent_starter_open_rate": 0.0,
        "opponent_extender_open_rate": 0.0,
        "opponent_interruption_open_rate": 0.0,
        "opponent_brick_rate": 0.0,
        "probability_weighted_resource_valid_rate": 0.0,
        "probability_weighted_stop_rate": 0.0,
        "probability_weighted_pivot_rate": 0.0,
        "probability_weighted_backup_rate": 0.0,
        "going_first_side_score": 0.0,
        "going_second_side_score": 0.0,
        "blocked_card_violations": [],
        "main_deck": [
          "Blue-Eyes Alternative White Dragon",
          "Blue-Eyes Jet Dragon",
          "Dragon Spirit of White",
          "Dragon Spirit of White",
          "Blue-Eyes Abyss Dragon",
          "Blue-Eyes Jet Dragon",
          "Blue-Eyes Alternative White Dragon",
          "Blue-Eyes Alternative White Dragon",
          "Blue-Eyes Abyss Dragon",
          "Blue-Eyes Jet Dragon",
          "The White Stone of Legend",
          "The White Stone of Legend",
          "Sage with Eyes of Blue",
          "Dictator of D.",
          "Sage with Eyes of Blue",
          "Bingo Machine, Go!!!",
          "Wishes for Eyes of Blue",
          "Bingo Machine, Go!!!",
          "Bingo Machine, Go!!!",
          "Wishes for Eyes of Blue",
          "The Ultimate Creature of Destruction",
          "Destined Rivals",
          "Chaos Dragon Levianeer",
          "Chaos Dragon Levianeer",
          "Chaos Dragon Levianeer",
          "Nibiru, the Primal Being",
          "Effect Veiler",
          "D.D. Crow",
          "Nibiru, the Primal Being",
          "Ghost Belle & Haunted Mansion",
          "Ghost Ogre & Snow Rabbit",
          "Book of Eclipse",
          "Dark Ruler No More",
          "Solemn Strike",
          "Solemn Judgment"
        ],
        "extra_deck": [
          "Dragon Master Knight",
          "Dragon Master Knight",
          "Blue-Eyes Spirit Dragon",
          "Blue-Eyes Tyrant Dragon",
          "Blue-Eyes Alternative Ultimate Dragon"
        ],
        "recommended_side_deck": [
          "Book of Eclipse",
          "Cosmic Cyclone",
          "Infinite Impermanence",
          "Effect Veiler",
          "Droll & Lock Bird",
          "True Light",
          "The Ultimate Creature of Destruction",
          "Droll Bird",
          "Dark Ruler No More",
          "Ash Blossom & Joyous Spring",
          "Zuttomozaurus",
          "Zuijin of the Ice Barrier",
          "Zubababa Knight",
          "Zubaba Knight",
          "Zubaba Buster"
        ],
        "side_cards_used": [
          "Effect Veiler",
          "Droll & Lock Bird",
          "Infinite Impermanence"
        ],
        "cards_sided_out": [
          "Dragon Spirit of White",
          "The Ultimate Creature of Destruction",
          "Solemn Strike"
        ]
      }
    ],
    "cache_hit": false
  }
}
