{
  "cache_version": "stabilization-a-v1",
  "value": {
    "engine_variant": "ritual",
    "matchup": "Branded curated profile",
    "going": "first",
    "successful_runs": 1,
    "failed_runs": 0,
    "failed_cell": false,
    "failure_rate": 0.0,
    "average_final_score": 277.59,
    "best_score": 277.59,
    "package_quality": 97.8,
    "playable_hand_rate": 1.0,
    "brick_rate": 0.0,
    "resilience_score": 8.7,
    "side_deck_score": 97.5,
    "game1_score": 276.64,
    "post_side_score": 279.92,
    "post_side_delta": 3.28,
    "post_side_valid_rate": 1.0,
    "valid_candidate_rate": 1.0,
    "side_optimization_success_rate": 1.0,
    "post_side_memory_used_rate": 0.0,
    "memory_aided_post_side_delta": 0,
    "matchup_coverage_score": 35.0,
    "choke_stop_rate": 0.87,
    "opponent_recovery_rate": 0.5138,
    "choke_coverage_score": 87.0,
    "best_interruption_overlap": 6,
    "poor_interruption_count": 1,
    "timing_precision_score": 0.7713,
    "pivot_risk_score": 0.7783,
    "best_timing_window_count": 3,
    "late_interruption_risk": 0.3333,
    "early_interruption_risk": 0.0,
    "backup_line_success_rate": 0.4749,
    "graph_stop_rate": 0.78,
    "graph_pivot_rate": 0.61,
    "graph_endboard_reduction_score": 0.4875,
    "graph_best_interruption_count": 2,
    "graph_poor_interruption_count": 3,
    "graph_timing_precision_score": 0.78,
    "opponent_resource_valid_rate": 1.0,
    "opponent_resource_failure_rate": 0.0,
    "opponent_pivot_success_rate": 0.0,
    "opponent_backup_success_rate": 0.6667,
    "opponent_starter_open_rate": 0.0,
    "opponent_extender_open_rate": 0.0,
    "opponent_interruption_open_rate": 0.0,
    "opponent_brick_rate": 0.0,
    "probability_weighted_resource_valid_rate": 0.0,
    "probability_weighted_stop_rate": 0.0,
    "probability_weighted_pivot_rate": 0.0,
    "probability_weighted_backup_rate": 0.0,
    "going_first_side_score": 20.0,
    "going_second_side_score": 8.0,
    "blocked_card_violations": [],
    "best_deck": {
      "main_deck": [
        "Blue-Eyes Alternative White Dragon",
        "Blue-Eyes Alternative White Dragon",
        "Blue-Eyes Jet Dragon",
        "Dragon Spirit of White",
        "Blue-Eyes Solid Dragon",
        "Dragon Spirit of White",
        "Blue-Eyes Alternative White Dragon",
        "Blue-Eyes Jet Dragon",
        "Dragon Spirit of White",
        "Blue-Eyes Solid Dragon",
        "Blue-Eyes Solid Dragon",
        "The White Stone of Ancients",
        "Bingo Machine, Go!!!",
        "The White Stone of Ancients",
        "Bingo Machine, Go!!!",
        "Sage with Eyes of Blue",
        "Sage with Eyes of Blue",
        "Maiden with Eyes of Blue",
        "The White Stone of Ancients",
        "Bingo Machine, Go!!!",
        "The White Stone of Legend",
        "Destined Rivals",
        "Destined Rivals",
        "Blue-Eyes Chaos MAX Dragon",
        "Blue-Eyes Chaos MAX Dragon",
        "Blue-Eyes Chaos Dragon",
        "Advanced Ritual Art",
        "Chaos Form",
        "Ghost Belle & Haunted Mansion",
        "Nibiru, the Primal Being",
        "Effect Veiler",
        "Ash Blossom & Joyous Spring",
        "Ghost Ogre & Snow Rabbit",
        "Ghost Ogre & Snow Rabbit",
        "Harpie's Feather Duster",
        "Lightning Storm",
        "Skill Drain",
        "Solemn Strike"
      ],
      "extra_deck": [
        "Blue-Eyes Twin Burst Dragon",
        "Neo Blue-Eyes Ultimate Dragon"
      ]
    },
    "recommended_side_deck": [
      [
        "Ash Blossom & Joyous Spring",
        1
      ],
      [
        "Droll & Lock Bird",
        1
      ],
      [
        "Ghost Belle & Haunted Mansion",
        1
      ],
      [
        "D.D. Crow",
        1
      ],
      [
        "Bystial Magnamhut",
        1
      ],
      [
        "Bystial Druiswurm",
        1
      ],
      [
        "Called by the Grave",
        1
      ],
      [
        "The Bystial Lubellion",
        1
      ],
      [
        "The Bystial Alba Los",
        1
      ],
      [
        "Etude of the Branded",
        1
      ],
      [
        "Effect Veiler",
        1
      ],
      [
        "Bystial Saronir",
        1
      ],
      [
        "Bystial Dis Pater",
        1
      ],
      [
        "Branded Befallen",
        1
      ],
      [
        "Branded Beast",
        1
      ]
    ],
    "best_remembered_side_cards": [],
    "best_remembered_side_out_cards": [],
    "runs": [
      {
        "run": 1,
        "ok": true,
        "engine_variant": "ritual",
        "final_score": 277.59,
        "package_quality": 97.8,
        "playable_hand_rate": 1.0,
        "brick_rate": 0.0,
        "resilience_score": 8.7,
        "side_deck_score": 97.5,
        "game1_score": 276.64,
        "post_side_score": 279.92,
        "post_side_delta": 3.28,
        "post_side_valid": true,
        "valid_candidate_rate": 1.0,
        "optimization_used": true,
        "post_side_memory_used": false,
        "remembered_side_cards": [],
        "remembered_side_out_cards": [],
        "memory_aided_post_side_delta": 0,
        "matchup_coverage_score": 35.0,
        "choke_stop_rate": 0.87,
        "opponent_recovery_rate": 0.5138,
        "choke_coverage_score": 87.0,
        "best_interruption_overlap": 6,
        "poor_interruption_count": 1,
        "timing_precision_score": 0.7713,
        "pivot_risk_score": 0.7783,
        "best_timing_window_count": 3,
        "late_interruption_risk": 0.3333,
        "early_interruption_risk": 0.0,
        "backup_line_success_rate": 0.4749,
        "graph_stop_rate": 0.78,
        "graph_pivot_rate": 0.61,
        "graph_endboard_reduction_score": 0.4875,
        "graph_best_interruption_count": 2,
        "graph_poor_interruption_count": 3,
        "graph_timing_precision_score": 0.78,
        "opponent_resource_valid_rate": 1.0,
        "opponent_resource_failure_rate": 0.0,
        "opponent_pivot_success_rate": 0.0,
        "opponent_backup_success_rate": 0.6667,
        "opponent_starter_open_rate": 0.0,
        "opponent_extender_open_rate": 0.0,
        "opponent_interruption_open_rate": 0.0,
        "opponent_brick_rate": 0.0,
        "probability_weighted_resource_valid_rate": 0.0,
        "probability_weighted_stop_rate": 0.0,
        "probability_weighted_pivot_rate": 0.0,
        "probability_weighted_backup_rate": 0.0,
        "going_first_side_score": 20.0,
        "going_second_side_score": 8.0,
        "blocked_card_violations": [],
        "main_deck": [
          "Blue-Eyes Alternative White Dragon",
          "Blue-Eyes Alternative White Dragon",
          "Blue-Eyes Jet Dragon",
          "Dragon Spirit of White",
          "Blue-Eyes Solid Dragon",
          "Dragon Spirit of White",
          "Blue-Eyes Alternative White Dragon",
          "Blue-Eyes Jet Dragon",
          "Dragon Spirit of White",
          "Blue-Eyes Solid Dragon",
          "Blue-Eyes Solid Dragon",
          "The White Stone of Ancients",
          "Bingo Machine, Go!!!",
          "The White Stone of Ancients",
          "Bingo Machine, Go!!!",
          "Sage with Eyes of Blue",
          "Sage with Eyes of Blue",
          "Maiden with Eyes of Blue",
          "The White Stone of Ancients",
          "Bingo Machine, Go!!!",
          "The White Stone of Legend",
          "Destined Rivals",
          "Destined Rivals",
          "Blue-Eyes Chaos MAX Dragon",
          "Blue-Eyes Chaos MAX Dragon",
          "Blue-Eyes Chaos Dragon",
          "Advanced Ritual Art",
          "Chaos Form",
          "Ghost Belle & Haunted Mansion",
          "Nibiru, the Primal Being",
          "Effect Veiler",
          "Ash Blossom & Joyous Spring",
          "Ghost Ogre & Snow Rabbit",
          "Ghost Ogre & Snow Rabbit",
          "Harpie's Feather Duster",
          "Lightning Storm",
          "Skill Drain",
          "Solemn Strike"
        ],
        "extra_deck": [
          "Blue-Eyes Twin Burst Dragon",
          "Neo Blue-Eyes Ultimate Dragon"
        ],
        "recommended_side_deck": [
          "Ash Blossom & Joyous Spring",
          "Droll & Lock Bird",
          "Ghost Belle & Haunted Mansion",
          "D.D. Crow",
          "Bystial Magnamhut",
          "Bystial Druiswurm",
          "Called by the Grave",
          "The Bystial Lubellion",
          "The Bystial Alba Los",
          "Etude of the Branded",
          "Effect Veiler",
          "Bystial Saronir",
          "Bystial Dis Pater",
          "Branded Befallen",
          "Branded Beast"
        ],
        "side_cards_used": [
          "Ash Blossom & Joyous Spring",
          "Droll & Lock Bird",
          "Ghost Belle & Haunted Mansion"
        ],
        "cards_sided_out": [
          "Lightning Storm",
          "Advanced Ritual Art",
          "Dragon Spirit of White"
        ]
      }
    ],
    "cache_hit": false
  }
}
